getexif/__init__.py
getexif/process.py
export_exif-2.0.0.dist-info/LICENSE
export_exif-2.0.0.dist-info/METADATA
export_exif-2.0.0.dist-info/WHEEL
export_exif-2.0.0.dist-info/top_level.txt
export_exif-2.0.0.dist-info/RECORD
