Metadata-Version: 2.1
Name: export-exif
Version: 2.0.0
Summary: Une bibliothèque pour traiter des images avec EXIF
Home-page: https://github.com/Jean-LouisB/ExifRecup.git
Author: Fabrice Kopf
Author-email: contact@fabricekopf.fr
Classifier: Programming Language :: Python :: 3
Classifier: License :: OSI Approved :: MIT License
Classifier: Operating System :: OS Independent
Requires-Python: >=3.7
License-File: LICENSE
Requires-Dist: exif
Requires-Dist: pathlib
